Metadata-Version: 1.1
Name: difftrack
Version: 0.8.2
Summary: Keep track of changes in data structures.
Home-page: https://github.com/qntln/difftrack
Author: Quantlane
Author-email: code@quantlane.com
License: Apache 2.0
Platform: UNKNOWN
Classifier: Development Status :: 4 - Beta
Classifier: License :: OSI Approved :: Apache Software License
Classifier: Natural Language :: English
Classifier: Programming Language :: Python :: 3 :: Only
Classifier: Programming Language :: Python :: 3.6
